{
  "presentationTitle": "Introduction to Machine Learning",
  "slides": [
    {
      "type": "title",
      "title": "Introduction to Machine Learning",
      "subtitle": "A Beginner's Guide to AI"
    },
    {
      "type": "content",
      "title": "What is Machine Learning?",
      "content": [
        "Machine Learning is a subset of Artificial Intelligence",
        "Enables computers to learn from data without explicit programming",
        "Uses algorithms to identify patterns and make decisions",
        "Applications: Image recognition, natural language processing, predictions"
      ]
    },
    {
      "type": "content",
      "title": "Types of Machine Learning",
      "content": [
        "<strong>Supervised Learning</strong>: Learning from labeled data",
        "<strong>Unsupervised Learning</strong>: Finding patterns in unlabeled data",
        "<strong>Reinforcement Learning</strong>: Learning through trial and error"
      ]
    },
    {
      "type": "two-column",
      "title": "Supervised vs Unsupervised",
      "leftContent": [
        "<h3>Supervised</h3>",
        "Labeled training data",
        "Predicts specific outcomes",
        "Examples: Classification, Regression"
      ],
      "rightContent": [
        "<h3>Unsupervised</h3>",
        "No labeled data",
        "Discovers hidden patterns",
        "Examples: Clustering, Dimensionality reduction"
      ]
    },
    {
      "type": "content",
      "title": "Thank You!",
      "content": [
        "Questions?",
        "<blockquote>\"The future belongs to those who learn.\"</blockquote>"
      ]
    }
  ]
}
